<xml version="1.0">
<dashboard>
	<widget field="Upper Hub Tarmac Cizgi" type="Boolean" class="edu.wpi.first.smartdashboard.gui.elements.BooleanBox">
		<location x="180" y="32"/>
		<height>27</height>
	</widget>
	<widget field="front_setpoint in mps" type="Number" class="edu.wpi.first.smartdashboard.gui.elements.TextBox">
		<location x="406" y="354"/>
	</widget>
	<widget field="shooter_encoder_rear_rps" type="Number" class="edu.wpi.first.smartdashboard.gui.elements.TextBox">
		<location x="13" y="469"/>
		<width>347</width>
	</widget>
	<widget field="shooter_encoder_front_rps" type="Number" class="edu.wpi.first.smartdashboard.gui.elements.TextBox">
		<location x="16" y="439"/>
	</widget>
	<widget field="rear_setpoint in rot" type="Number" class="edu.wpi.first.smartdashboard.gui.elements.TextBox">
		<location x="16" y="400"/>
		<width>345</width>
	</widget>
	<widget field="rear_setpoint in mps" type="Number" class="edu.wpi.first.smartdashboard.gui.elements.TextBox">
		<location x="408" y="385"/>
		<width>297</width>
		<height>25</height>
	</widget>
	<widget field="front_setpoint in rot" type="Number" class="edu.wpi.first.smartdashboard.gui.elements.TextBox">
		<location x="17" y="371"/>
		<width>343</width>
	</widget>
	<widget field="hubYaw" type="Number" class="edu.wpi.first.smartdashboard.gui.elements.TextBox">
		<location x="295" y="261"/>
		<width>169</width>
	</widget>
	<widget field="GORUS" type="Boolean" class="edu.wpi.first.smartdashboard.gui.elements.BooleanBox">
		<location x="293" y="219"/>
		<width>173</width>
		<height>15</height>
	</widget>
	<widget field="hubDistance" type="Number" class="edu.wpi.first.smartdashboard.gui.elements.TextBox">
		<location x="294" y="240"/>
		<width>169</width>
	</widget>
	<widget field="Lower Hub" type="Boolean" class="edu.wpi.first.smartdashboard.gui.elements.BooleanBox">
		<location x="367" y="30"/>
		<width>87</width>
		<height>29</height>
	</widget>
	<widget field="Upper Hub" type="Boolean" class="edu.wpi.first.smartdashboard.gui.elements.BooleanBox">
		<location x="472" y="32"/>
		<width>85</width>
		<height>27</height>
	</widget>
	<widget field="Upper Hub 2 Metre" type="Boolean" class="edu.wpi.first.smartdashboard.gui.elements.BooleanBox">
		<location x="575" y="32"/>
		<width>142</width>
		<height>26</height>
	</widget>
	<static-widget class="edu.wpi.first.smartdashboard.gui.elements.Label">
		<location x="504" y="208"/>
		<property name="Text" value="BAGLANTI"/>
	</static-widget>
	<static-widget class="edu.wpi.first.smartdashboard.gui.elements.ConnectionIndicator">
		<location x="559" y="235"/>
		<width>156</width>
		<height>78</height>
	</static-widget>
	<static-widget class="edu.wpi.first.smartdashboard.gui.elements.Label">
		<location x="137" y="192"/>
		<property name="Text" value="TOP SAYISI"/>
	</static-widget>
	<widget field="ballCount" type="Number" class="edu.wpi.first.smartdashboard.gui.elements.SimpleDial">
		<location x="40" y="214"/>
		<property name="Upper Limit" value="2.0"/>
	</widget>
	<static-widget class="edu.wpi.first.smartdashboard.gui.elements.Label">
		<location x="232" y="98"/>
		<property name="Text" value="SHOOTER"/>
	</static-widget>
	<static-widget class="edu.wpi.first.smartdashboard.gui.elements.Label">
		<location x="84" y="96"/>
		<width>48</width>
		<height>14</height>
		<property name="Text" value="INTAKE"/>
	</static-widget>
	<widget field="shooterRunning" type="Boolean" class="edu.wpi.first.smartdashboard.gui.elements.BooleanBox">
		<location x="224" y="121"/>
		<width>137</width>
		<height>57</height>
	</widget>
	<widget field="IntakeState" type="String" class="edu.wpi.first.smartdashboard.gui.elements.FormattedField">
		<location x="390" y="120"/>
		<width>239</width>
		<height>21</height>
		<property name="Background" value="255.0.51.255"/>
	</widget>
	<widget field="shooterState" type="String" class="edu.wpi.first.smartdashboard.gui.elements.FormattedField">
		<location x="384" y="143"/>
		<width>246</width>
		<height>22</height>
		<property name="Background" value="255.0.0.255"/>
	</widget>
	<widget field="Autonomous Mode" type="String Chooser" class="edu.wpi.first.smartdashboard.gui.elements.Chooser">
		<location x="9" y="8"/>
	</widget>
	<widget field="intakeRunning" type="Boolean" class="edu.wpi.first.smartdashboard.gui.elements.BooleanBox">
		<location x="71" y="121"/>
		<width>138</width>
		<height>53</height>
	</widget>
</dashboard>
<live-window>
	<widget field="Ungrouped" type="LW Subsystem" class="edu.wpi.first.smartdashboard.livewindow.elements.LWSubsystem">
		<widget field="DigitalInput[0]" type="Digital Input" class="edu.wpi.first.smartdashboard.livewindow.elements.DigitalInputDisplay">
			<location x="5" y="20"/>
			<height>24</height>
			<width>361</width>
		</widget>
		<widget field="DigitalInput[6]" type="Digital Input" class="edu.wpi.first.smartdashboard.livewindow.elements.DigitalInputDisplay">
			<location x="5" y="44"/>
			<height>24</height>
			<width>361</width>
		</widget>
		<widget field="DigitalInput[8]" type="Digital Input" class="edu.wpi.first.smartdashboard.livewindow.elements.DigitalInputDisplay">
			<location x="5" y="68"/>
			<height>24</height>
			<width>361</width>
		</widget>
		<widget field="Encoder[5]" type="Quadrature Encoder" class="edu.wpi.first.smartdashboard.livewindow.elements.EncoderDisplay">
			<location x="5" y="92"/>
			<height>123</height>
			<width>361</width>
		</widget>
		<widget field="PWMVictorSPX[2]" type="Motor Controller" class="edu.wpi.first.smartdashboard.livewindow.elements.SpeedController">
			<location x="5" y="215"/>
			<height>62</height>
			<width>361</width>
		</widget>
		<widget field="DigitalInput[5]" type="Digital Input" class="edu.wpi.first.smartdashboard.livewindow.elements.DigitalInputDisplay">
			<location x="5" y="277"/>
			<height>24</height>
			<width>361</width>
		</widget>
		<widget field="DigitalInput[7]" type="Digital Input" class="edu.wpi.first.smartdashboard.livewindow.elements.DigitalInputDisplay">
			<location x="5" y="301"/>
			<height>24</height>
			<width>361</width>
		</widget>
		<widget field="PWMVictorSPX[3]" type="Motor Controller" class="edu.wpi.first.smartdashboard.livewindow.elements.SpeedController">
			<location x="5" y="325"/>
			<height>62</height>
			<width>361</width>
		</widget>
		<widget field="DigitalInput[4]" type="Digital Input" class="edu.wpi.first.smartdashboard.livewindow.elements.DigitalInputDisplay">
			<location x="5" y="387"/>
			<height>24</height>
			<width>361</width>
		</widget>
		<widget field="Encoder[8]" type="Quadrature Encoder" class="edu.wpi.first.smartdashboard.livewindow.elements.EncoderDisplay">
			<location x="5" y="411"/>
			<height>123</height>
			<width>361</width>
		</widget>
		<widget field="PWMVictorSPX[0]" type="Motor Controller" class="edu.wpi.first.smartdashboard.livewindow.elements.SpeedController">
			<location x="5" y="534"/>
			<height>62</height>
			<width>361</width>
		</widget>
		<widget field="Encoder[0]" type="Quadrature Encoder" class="edu.wpi.first.smartdashboard.livewindow.elements.EncoderDisplay">
			<location x="5" y="596"/>
			<height>123</height>
			<width>361</width>
		</widget>
		<widget field="DigitalInput[3]" type="Digital Input" class="edu.wpi.first.smartdashboard.livewindow.elements.DigitalInputDisplay">
			<location x="5" y="719"/>
			<height>24</height>
			<width>361</width>
		</widget>
		<widget field="PWMVictorSPX[1]" type="Motor Controller" class="edu.wpi.first.smartdashboard.livewindow.elements.SpeedController">
			<location x="5" y="743"/>
			<height>62</height>
			<width>361</width>
		</widget>
		<widget field="DigitalInput[1]" type="Digital Input" class="edu.wpi.first.smartdashboard.livewindow.elements.DigitalInputDisplay">
			<location x="5" y="805"/>
			<height>24</height>
			<width>361</width>
		</widget>
		<widget field="DigitalInput[9]" type="Digital Input" class="edu.wpi.first.smartdashboard.livewindow.elements.DigitalInputDisplay">
			<location x="5" y="829"/>
			<height>24</height>
			<width>361</width>
		</widget>
		<location x="14" y="9"/>
		<width>371</width>
		<height>858</height>
	</widget>
</live-window>
	<hidden field="auto_forwardControllerSetpoint"/>
	<hidden field="auto_turnControllerSetpoint"/>
	<hidden field="shooter_valueRear"/>
	<hidden field="atis_kontrol"/>
	<hidden field="auto_botInPlace"/>
	<hidden field="climbMotor1"/>
	<hidden field="shooter_valueFront"/>
	<hidden field="climbMotor2"/>
	<hidden field="Lower Hub Dipdibe"/>
	<hidden field="Field"/>
	<hidden field="Model"/>
	<hidden field="PIDController[1]"/>
	<hidden field="atis_Kontrol"/>
	<hidden field="shooter_encoder"/>
</xml>